app.py
gradle/__init__.py
gradle/gradle_manager.py
gradle/gradle_wrapper.py
gradle/dto/gradle_error.py
gradle/dto/task.py
gradle/dto/task_list.py
gradle/dto/task_metadata.py
lazygradle-1.1.7.dist-info/licenses/LICENSE
ui/__init__.py
ui/confirmation_modal.py
ui/gradle_project_changer.py
ui/gradle_project_task_viewer.py
ui/gradlew_permission_modal.py
ui/lazy_gradle_app.css
ui/lazy_gradle_app.py
ui/project_chooser_modal.py
ui/run_task_output.py
ui/run_task_with_parameters_modal.py
ui/task_manager_widget.py
ui/task_tracker.py
ui/widget.py
lazygradle-1.1.7.dist-info/METADATA
lazygradle-1.1.7.dist-info/WHEEL
lazygradle-1.1.7.dist-info/entry_points.txt
lazygradle-1.1.7.dist-info/top_level.txt
lazygradle-1.1.7.dist-info/RECORD
