Metadata-Version: 2.4
Name: lazygradle
Version: 1.1.7
Summary: A TUI for managing and running your Gradle tasks
Author-email: jacob-sabella <jacobsabella@outlook.com>
License-Expression: MIT
Project-URL: Homepage, https://github.com/jacob-sabella/lazygradle
Project-URL: Issues, https://github.com/jacob-sabella/lazygradle/issues
Keywords: gradle,tui,build-tool,terminal
Classifier: Programming Language :: Python :: 3
Classifier: Programming Language :: Python :: 3.13
Classifier: Operating System :: OS Independent
Classifier: Environment :: Console
Classifier: Topic :: Software Development :: Build Tools
Requires-Python: >=3.13
License-File: LICENSE
Requires-Dist: textual
Dynamic: license-file
